ddmail_email_remover/__init__.py
ddmail_email_remover/application.py
ddmail_email_remover-0.0.2.dist-info/METADATA
ddmail_email_remover-0.0.2.dist-info/WHEEL
ddmail_email_remover-0.0.2.dist-info/licenses/LICENSE
ddmail_email_remover-0.0.2.dist-info/RECORD
