Metadata-Version: 2.4
Name: ddmail_email_remover
Version: 0.0.2
Summary: Web application API for removing email accounts on disc for the DDMail project.
Project-URL: Homepage, https://github.com/drzobin/ddmail_email_remover
Project-URL: Issues, https://github.com/drzobin/ddmail_email_remover/issues
Author-email: Robin Larsson <me@drz.se>
License-Expression: AGPL-3.0
License-File: LICENSE
Classifier: Operating System :: POSIX :: Linux
Classifier: Programming Language :: Python :: 3
Requires-Python: >=3.8
Requires-Dist: argon2-cffi
Requires-Dist: ddmail-validators
Requires-Dist: flask
Requires-Dist: gunicorn
Requires-Dist: toml
Provides-Extra: dev
Requires-Dist: argon2-cffi; extra == 'dev'
Requires-Dist: ddmail-validators; extra == 'dev'
Requires-Dist: flake8; extra == 'dev'
Requires-Dist: flask; extra == 'dev'
Requires-Dist: gunicorn; extra == 'dev'
Requires-Dist: hatchling; extra == 'dev'
Requires-Dist: pytest-cov; extra == 'dev'
Requires-Dist: toml; extra == 'dev'
Requires-Dist: twine; extra == 'dev'
Provides-Extra: test
Requires-Dist: argon2-cffi; extra == 'test'
Requires-Dist: ddmail-validators; extra == 'test'
Requires-Dist: flake8; extra == 'test'
Requires-Dist: flask; extra == 'test'
Requires-Dist: gunicorn; extra == 'test'
Requires-Dist: pytest-cov; extra == 'test'
Requires-Dist: toml; extra == 'test'
